vestas_azure/__init__.py
vestas_azure/blob_storage.py
vestas_azure/config.py
vestas_azure/dataframe_container.py
vestas_azure/file_container.py
vestas_azure/logging.py
vestas_azure/service_bus.py
vestas_azure/utils.py
vestas_azure-0.1.10rc4.dist-info/WHEEL
vestas_azure-0.1.10rc4.dist-info/METADATA
vestas_azure-0.1.10rc4.dist-info/RECORD
