Metadata-Version: 2.1
Name: vestas-azure
Version: 0.1.10rc4
Summary: 
License: Proprietary
Author: Emil Haldrup Eriksen
Author-email: emher@vestas.com
Requires-Python: >=3.9,<4
Classifier: License :: Other/Proprietary License
Classifier: Programming Language :: Python :: 3
Classifier: Programming Language :: Python :: 3.9
Classifier: Programming Language :: Python :: 3.10
Requires-Dist: adlfs (>=2022.7.0,<2023.0.0)
Requires-Dist: azure-identity (>=1.10.0,<2.0.0)
Requires-Dist: azure-keyvault-secrets (>=4.5.1,<5.0.0)
Requires-Dist: azure-servicebus (>=7.7.0,<8.0.0)
Requires-Dist: jsonformatter (>=0.3.1,<0.4.0)
Requires-Dist: pyarrow (>=8.0.0,<9.0.0)
Requires-Dist: pydantic (>=1.9.1,<2.0.0)
Requires-Dist: python-dotenv (>=0.20.0,<0.21.0)
